pcubit/__init__.py
pcubit/base.py
pcubit/core.py
pcubit/stats.py
pcubit/tests/__init__.py
pcubit/tests/__main__.py
pcubit/tests/test_examples.py
pcubit/tests/test_many.py
pcubit/tests/test_one.py
pcubit/tests/test_style.py
pcubit/tests/test_zero.py
pcubit-0.2.0.dist-info/licenses/LICENSE
pcubit-0.2.0.dist-info/METADATA
pcubit-0.2.0.dist-info/WHEEL
pcubit-0.2.0.dist-info/top_level.txt
pcubit-0.2.0.dist-info/RECORD
