Metadata-Version: 2.4
Name: pCubit
Version: 0.2.0
Summary: Placement of particles/pores using Cubit.
Author: Michael R. Buche
Author-email: mrbuche@sandia.gov
Project-URL: Documentation, https://pcubit.readthedocs.io
Project-URL: Homepage, https://sandialabs.github.io/pCubit
Project-URL: Repository, https://github.com/sandialabs/pCubit
Classifier: License :: OSI Approved :: BSD License
Classifier: Development Status :: 5 - Production/Stable
Classifier: Intended Audience :: Science/Research
Classifier: Topic :: Scientific/Engineering
Classifier: Programming Language :: Python
License-File: LICENSE
Requires-Dist: numpy
Requires-Dist: scipy
Dynamic: license-file
